chroma_tui/__init__.py
chroma_tui/main.py
chroma_tui/tui_rich.py
chroma_tui-0.1.1.dist-info/METADATA
chroma_tui-0.1.1.dist-info/WHEEL
chroma_tui-0.1.1.dist-info/entry_points.txt
chroma_tui-0.1.1.dist-info/top_level.txt
chroma_tui-0.1.1.dist-info/RECORD
