Metadata-Version: 2.4
Name: chroma-tui
Version: 0.1.1
Summary: A TUI for ChromaDB
Author-email: Thups Mukhunyeledzi <muthupheimukhunyeledzi@gmail.com>
Classifier: Programming Language :: Python :: 3
Classifier: License :: OSI Approved :: MIT License
Classifier: Operating System :: OS Independent
Requires-Python: >=3.8
Requires-Dist: textual
Requires-Dist: chromadb
